ezserialize/__init__.py
ezserialize/ezserialize.py
ezserialize-1.0.dist-info/LICENSE
ezserialize-1.0.dist-info/METADATA
ezserialize-1.0.dist-info/WHEEL
ezserialize-1.0.dist-info/top_level.txt
ezserialize-1.0.dist-info/RECORD
