Metadata-Version: 2.1
Name: ezserialize
Version: 1.0
Summary: Easy to use python json serializer and deserializer tool using syntax similar to dataclasses
Author-email: Damus666 <macchia.cuordileone@gmail.com>
Project-URL: homepage, https://github.com/Damus666/EzSerialize
Project-URL: bugtracker, https://github.com/Damus666/EzSerialize/issues
Classifier: Programming Language :: Python :: 3
Classifier: License :: OSI Approved :: MIT License
Classifier: Operating System :: OS Independent
Requires-Python: >=3.11
License-File: LICENSE
